Metadata-Version: 2.1
Name: MatQUBO
Version: 0.0
Summary: MatQUBO
Home-page: UNKNOWN
Author-email: aryatahlil@yahoo.com
License: UNKNOWN
Platform: UNKNOWN
